req_test_align/__init__.py
req_test_align/__main__.py
req_test_align/config.py
req_test_align/configure.py
req_test_align/main.py
req_test_align/types.py
req_test_align/ci/__init__.py
req_test_align/ci/git.py
req_test_align/ci/github.py
req_test_align/core/__init__.py
req_test_align/core/ai_client.py
req_test_align/core/align_test_case.py
req_test_align/monitor/__init__.py
req_test_align/monitor/resource_monitor.py
req_test_align/templates/github-pr.yml
req_test_align/utils/__init__.py
req_test_align/utils/commit_utils.py
req_test_align/utils/java_utils.py
req_test_align/utils/logger.py
req_test_align/utils/python_utils.py
req_test_align/utils/utils.py
req_test_align-0.1.4.dist-info/licenses/LICENSE
req_test_align-0.1.4.dist-info/METADATA
req_test_align-0.1.4.dist-info/WHEEL
req_test_align-0.1.4.dist-info/entry_points.txt
req_test_align-0.1.4.dist-info/top_level.txt
req_test_align-0.1.4.dist-info/RECORD
